setup.py
blueprint_io/__init__.py
blueprint_io/cfg.py
blueprint_io/http.py
blueprint_io.egg-info/PKG-INFO
blueprint_io.egg-info/SOURCES.txt
blueprint_io.egg-info/dependency_links.txt
blueprint_io.egg-info/not-zip-safe
blueprint_io.egg-info/requires.txt
blueprint_io.egg-info/top_level.txt