Metadata-Version: 1.0
Name: blueprint-io
Version: 0.1.0
Summary: centralized blueprint service client
Home-page: http://devstructure.com/
Author: Richard Crowley
Author-email: richard@devstructure.com
License: BSD
Platform: UNKNOWN
